autoad/__init__.py
autoad/logging_utils.py
autoad/main.py
autoad-0.1.5.dist-info/WHEEL
autoad-0.1.5.dist-info/entry_points.txt
autoad-0.1.5.dist-info/METADATA
autoad-0.1.5.dist-info/RECORD
