Metadata-Version: 2.3
Name: autoad
Version: 0.1.5
Summary: A simple automatic algorithm design tool
Requires-Dist: pytest>=8.4.1
Requires-Python: >=3.10
